{
  "name": "mana_machine_macerator",
  "progressTexture": "multiblocked:textures/gui/progress_bar_arrow.png",
  "fuelTexture": "multiblocked:textures/gui/progress_bar_fuel.png",
  "recipes": [
    {
      "uid": "c665eb16-8e4c-4680-abcb-940292bebc23",
      "duration": 1,
      "inputs": {
        "item": [
          {
            "chance": 0.0,
            "content": {
              "amount": 1,
              "matches": [
                "{id:\"contenttweaker:upgrade_x64\",Count:1,Damage:0s}"
              ]
            }
          },
          {
            "chance": 1.0,
            "content": {
              "amount": 64,
              "matches": [
                "{id:\"minecraft:iron_ore\",Count:64,Damage:0s}"
              ]
            }
          }
        ],
        "bot_mana": [
          {
            "chance": 0.005,
            "content": 6400
          }
        ]
      },
      "outputs": {
        "item": [
          {
            "chance": 1.0,
            "content": {
              "amount": 128,
              "matches": [
                "{id:\"industrialupgrade:crushed\",Count:128,Damage:21s}"
              ]
            }
          }
        ]
      },
      "tickInputs": {
        "bot_mana": [
          {
            "chance": 1.0,
            "content": 4200
          }
        ]
      }
    },
    {
      "uid": "30c1ebfc-1332-4d26-a1f4-f1b09bf4b178",
      "duration": 8,
      "inputs": {
        "item": [
          {
            "chance": 0.0,
            "content": {
              "amount": 1,
              "matches": [
                "{id:\"contenttweaker:upgrade_x9\",Count:1,Damage:0s}"
              ]
            }
          },
          {
            "chance": 1.0,
            "content": {
              "amount": 9,
              "matches": [
                "{id:\"minecraft:iron_ore\",Count:9,Damage:0s}"
              ]
            }
          }
        ],
        "bot_mana": [
          {
            "chance": 0.009,
            "content": 900
          }
        ]
      },
      "outputs": {
        "item": [
          {
            "chance": 1.0,
            "content": {
              "amount": 18,
              "matches": [
                "{id:\"industrialupgrade:crushed\",Count:18,Damage:21s}"
              ]
            }
          }
        ]
      },
      "tickInputs": {
        "bot_mana": [
          {
            "chance": 1.0,
            "content": 35
          }
        ]
      }
    },
    {
      "uid": "ce070fc1-181c-4776-9835-04c39ca8b6e8",
      "duration": 20,
      "inputs": {
        "item": [
          {
            "chance": 0.0,
            "content": {
              "amount": 1,
              "matches": [
                "{id:\"contenttweaker:upgrade_x1\",Count:1,Damage:0s}"
              ]
            }
          },
          {
            "chance": 1.0,
            "content": {
              "amount": 1,
              "matches": [
                "{id:\"minecraft:iron_ore\",Count:1,Damage:0s}"
              ]
            }
          }
        ]
      },
      "outputs": {
        "item": [
          {
            "chance": 1.0,
            "content": {
              "amount": 2,
              "matches": [
                "{id:\"industrialupgrade:crushed\",Count:2,Damage:21s}"
              ]
            }
          }
        ]
      },
      "tickInputs": {
        "bot_mana": [
          {
            "chance": 1.0,
            "content": 3
          }
        ]
      }
    },
    {
      "uid": "832a108d-2608-48b4-8581-9a42b2fb4096",
      "duration": 15,
      "inputs": {
        "item": [
          {
            "chance": 0.0,
            "content": {
              "amount": 1,
              "matches": [
                "{id:\"contenttweaker:upgrade_x3\",Count:1,Damage:0s}"
              ]
            }
          },
          {
            "chance": 1.0,
            "content": {
              "amount": 3,
              "matches": [
                "{id:\"minecraft:iron_ore\",Count:3,Damage:0s}"
              ]
            }
          }
        ],
        "bot_mana": [
          {
            "chance": 0.02,
            "content": 300
          }
        ]
      },
      "outputs": {
        "item": [
          {
            "chance": 1.0,
            "content": {
              "amount": 6,
              "matches": [
                "{id:\"industrialupgrade:crushed\",Count:6,Damage:21s}"
              ]
            }
          }
        ]
      },
      "tickInputs": {
        "bot_mana": [
          {
            "chance": 1.0,
            "content": 4
          }
        ]
      }
    }
  ]
}